easypredict/__init__.py
easypredict/easypredict.py
easypredict-0.0.1.dist-info/DESCRIPTION.rst
easypredict-0.0.1.dist-info/METADATA
easypredict-0.0.1.dist-info/RECORD
easypredict-0.0.1.dist-info/WHEEL
easypredict-0.0.1.dist-info/metadata.json
easypredict-0.0.1.dist-info/top_level.txt
